validata_ui/__init__.py
validata_ui/config.py
validata_ui/model.py
validata_ui/pdf_renderer.py
validata_ui/ui_util.py
validata_ui/validata_util.py
validata_ui/views.py
validata_ui/static/validata.css
validata_ui/static/validata_popover.js
validata_ui/static/img/favicon.ico
validata_ui/static/img/logo-horizontal.png
validata_ui/static/img/logo-only.png
validata_ui/templates/_sentry.html
validata_ui/templates/base_template.html
validata_ui/templates/home.html
validata_ui/templates/schema_info_macros.html
validata_ui/templates/validation_form.html
validata_ui/templates/validation_macros.html
validata_ui/templates/validation_report.html
validata_ui-0.7.9.dist-info/LICENSE
validata_ui-0.7.9.dist-info/METADATA
validata_ui-0.7.9.dist-info/WHEEL
validata_ui-0.7.9.dist-info/top_level.txt
validata_ui-0.7.9.dist-info/zip-safe
validata_ui-0.7.9.dist-info/RECORD
