Metadata-Version: 2.1
Name: validata-ui
Version: 0.7.9
Summary: Validata Web UI
Home-page: https://gitlab.com/validata-table/validata-ui
Author: Validata team
Author-email: admin-validata@jailbreak.paris
License: AGPLv3
Platform: UNKNOWN
Classifier: Development Status :: 5 - Production/Stable
Classifier: Intended Audience :: Developers
Classifier: Topic :: Software Development :: Libraries :: Python Modules
Classifier: Operating System :: OS Independent
Classifier: License :: OSI Approved :: GNU Affero General Public License v3
Classifier: Programming Language :: Python :: 3
License-File: LICENSE
Requires-Dist: commonmark
Requires-Dist: ezodf
Requires-Dist: flask ==2.1.2
Requires-Dist: frictionless ==4.38.0
Requires-Dist: lxml
Requires-Dist: pydantic ==1.10.9
Requires-Dist: python-dotenv
Requires-Dist: pyyaml
Requires-Dist: requests
Requires-Dist: requests-cache ==0.9.4
Requires-Dist: toml
Requires-Dist: opendataschema
Requires-Dist: validata-core ==0.9.7
Provides-Extra: sentry
Requires-Dist: sentry-sdk[flask] ; extra == 'sentry'
